[
  {
    "text": "S.S.SURGICAL",
    "label": "Text",
    "region": "middle-left"
  },
  {
    "text": "Y CENTREWholesale[PARTY]",
    "label": "Text",
    "region": "lower-left"
  },
  {
    "text": "SHREE GANESH ALUMINIUM",
    "label": "Section-Header",
    "region": "middle-left"
  },
  {
    "text": "10/20/22, Manikpur Road, B.J. Complex, Patna, Bihar, 800014Dealer in Aluminium, Surface Care, Aluminium Shutters, Aluminium Windows, Aluminium Doors, C.I. A.C. Sheet & P.V.C. Sheet,P.V.C. Profile, Thermosteel, Ladder & HW Etc.",
    "label": "Text",
    "region": "lower-left"
  }
]